pynosql/__init__.py
pynosql/base/__init__.py
pynosql/base/base_model.py
pynosql/base/model.py
pynosql/clients/__init__.py
pynosql/clients/aws.py
pynosql/clients/aws_mock.py
pynosql/clients/base_client.py
pynosql/common/__init__.py
pynosql/common/base_model_helper.py
pynosql/common/model_helper.py
pynosql/credentials/__init__.py
pynosql/credentials/aws.py
pynosql/credentials/base_credentials.py
pynosql/credentials/mongo.py
pynosql/providers/__init__.py
pynosql/providers/base_provider.py
pynosql/providers/dynamo.py
pynosql/test/__init__.py
pynosql/test/client_test.py
pynosql/test/credentials_test.py
pynosql/test/dynamo_test.py
pynosql/test/model_test.py
pynosql-0.0.4.dist-info/LICENSE
pynosql-0.0.4.dist-info/METADATA
pynosql-0.0.4.dist-info/WHEEL
pynosql-0.0.4.dist-info/top_level.txt
pynosql-0.0.4.dist-info/RECORD
