Metadata-Version: 2.1
Name: pynosql
Version: 0.0.4
Summary: A NOSQL DB Library for Python
Home-page: https://github.com/stajkowski/pynosql
Author: Brian Stajkowski
Author-email: stajkowski100@gmail.com
License: UNKNOWN
Platform: UNKNOWN
Classifier: Programming Language :: Python :: 3
Classifier: License :: OSI Approved :: MIT License
Classifier: Operating System :: OS Independent
